py_fpff.py
py_fpff-1.0.0.dist-info/LICENSE
py_fpff-1.0.0.dist-info/METADATA
py_fpff-1.0.0.dist-info/WHEEL
py_fpff-1.0.0.dist-info/top_level.txt
py_fpff-1.0.0.dist-info/RECORD
