Metadata-Version: 2.1
Name: py-fpff
Version: 1.0.0
Summary: Library for working with FPFF
Home-page: https://github.com/jasmaa/py-fpff
Author: Jason Maa
License: UNKNOWN
Platform: UNKNOWN
License-File: LICENSE
